{"type":"FeatureCollection","query":["abu","dhabi"],"features":[{"id":"province.2556816964","type":"Feature","text":"Abu Dhabi","place_name":"Abu Dhabi, United Arab Emirates","relevance":1,"center":[53.683484,23.797272],"geometry":{"type":"Point","coordinates":[53.683484,23.797272]},"bbox":[51.56934655000331,22.620945943300665,55.99785282424847,25.249416408340615],"properties":{"title":"Abu Dhabi"},"context":[{"id":"country.1827899765","text":"United Arab Emirates"}]},{"id":"city.11940330","type":"Feature","text":"Abu Dhabi","place_name":"Abu Dhabi, Abu Dhabi, United Arab Emirates","relevance":1,"center":[54.395267,24.449406],"geometry":{"type":"Point","coordinates":[54.395267,24.449406]},"bbox":[54.29082900000002,24.362686000000007,54.61956000000001,24.53576299999999],"properties":{"title":"Abu Dhabi"},"context":[{"id":"province.2556816964","text":"Abu Dhabi"},{"id":"country.1827899765","text":"United Arab Emirates"}]}],"attribution":"<a href='https://www.mapbox.com/about/maps/' target='_blank'>&copy; Mapbox</a>"}