{"type":"FeatureCollection","query":["beirut"],"features":[{"id":"province.3885937891","type":"Feature","text":"Beirut","place_name":"Beirut, Lebanon","relevance":1,"center":[35.509952,33.889065],"geometry":{"type":"Point","coordinates":[35.509952,33.889065]},"bbox":[35.47046959709429,33.86180939428817,35.54809312349892,33.91299062761543],"properties":{"title":"Beirut"},"context":[{"id":"country.237760293","text":"Lebanon"}]},{"id":"city.11960307","type":"Feature","text":"Beirut","place_name":"Beirut, Beirut, Lebanon","relevance":1,"center":[35.516328,33.884577],"geometry":{"type":"Point","coordinates":[35.516328,33.884577]},"bbox":[35.452194000000006,33.84261699999998,35.60325600000002,33.92797899999999],"properties":{"title":"Beirut"},"context":[{"id":"province.3885937891","text":"Beirut"},{"id":"country.237760293","text":"Lebanon"}]}],"attribution":"<a href='https://www.mapbox.com/about/maps/' target='_blank'>&copy; Mapbox</a>"}