{"type":"FeatureCollection","query":["hamburg"],"features":[{"id":"province.4046327072","type":"Feature","text":"Hamburg","place_name":"Hamburg, Germany","relevance":1,"center":[9.941334,53.56701],"geometry":{"type":"Point","coordinates":[9.941334,53.56701]},"bbox":[8.485107999999798,53.395000499999846,10.32595899999979,53.93131549999981],"properties":{"title":"Hamburg"},"context":[{"id":"country.593090590","text":"Germany"}]},{"id":"city.10656958","type":"Feature","text":"Hamburg","place_name":"Hamburg, Hamburg, Germany","relevance":1,"center":[9.94713,53.550731],"geometry":{"type":"Point","coordinates":[9.94713,53.550731]},"bbox":[9.672087999999995,53.36654699999998,10.36999999999999,53.745716000000016],"properties":{"title":"Hamburg"},"context":[{"id":"province.4046327072","text":"Hamburg"},{"id":"country.593090590","text":"Germany"}]},{"id":"city.71646","type":"Feature","text":"Hamburg","place_name":"Hamburg, 71646, Arkansas, United States","relevance":1,"center":[-91.781734,33.230281],"geometry":{"type":"Point","coordinates":[-91.781734,33.230281]},"bbox":[-92.04231297808364,33.00700246699315,-91.5622200201088,33.453077493981226],"properties":{"title":"Hamburg"},"context":[{"id":"postcode-us.1794979500","text":"71646"},{"id":"province.3855330187","text":"Arkansas"},{"id":"country.4150104525","text":"United States"}]},{"id":"city.51640","type":"Feature","text":"Hamburg","place_name":"Hamburg, 51640, Iowa, United States","relevance":1,"center":[-95.669489,40.623519],"geometry":{"type":"Point","coordinates":[-95.669489,40.623519]},"bbox":[-95.77471282618183,40.51218417395937,-95.37381501702407,40.73466480360033],"properties":{"title":"Hamburg"},"context":[{"id":"postcode-us.3554754979","text":"51640"},{"id":"province.3529999094","text":"Iowa"},{"id":"country.4150104525","text":"United States"}]},{"id":"city.19526","type":"Feature","text":"Hamburg","place_name":"Hamburg, 19526, Pennsylvania, United States","relevance":1,"center":[-76.023312,40.55257],"geometry":{"type":"Point","coordinates":[-76.023312,40.55257]},"bbox":[-76.12992794899309,40.475085235825354,-75.85249302655126,40.6299778173049],"properties":{"title":"Hamburg"},"context":[{"id":"postcode-us.1335395061","text":"19526"},{"id":"province.2184819983","text":"Pennsylvania"},{"id":"country.4150104525","text":"United States"}]}],"attribution":"<a href='https://www.mapbox.com/about/maps/' target='_blank'>&copy; Mapbox</a>"}