{"type":"FeatureCollection","query":["jeddah"],"features":[{"id":"city.11939873","type":"Feature","text":"Jeddah","place_name":"Jeddah, Makkah, Saudi Arabia","relevance":1,"center":[39.173388,21.583105],"geometry":{"type":"Point","coordinates":[39.173388,21.583105]},"bbox":[39.047565000000006,21.314671999999998,39.31667700000001,21.81704100000001],"properties":{"title":"Jeddah"},"context":[{"id":"province.4149686040","text":"Makkah"},{"id":"country.3267341775","text":"Saudi Arabia"}]}],"attribution":"<a href='https://www.mapbox.com/about/maps/' target='_blank'>&copy; Mapbox</a>"}