{"type":"FeatureCollection","query":["manchester"],"features":[{"id":"province.3082689761","type":"Feature","text":"Manchester","place_name":"Manchester, Jamaica","relevance":1,"center":[-77.51811,18.050003],"geometry":{"type":"Point","coordinates":[-77.51811,18.050003]},"bbox":[-77.64029415615033,17.84194570543001,-77.3589676581309,18.237233384812892],"properties":{"title":"Manchester"},"context":[{"id":"country.2792236698","text":"Jamaica"}]},{"id":"city.40962","type":"Feature","text":"Manchester","place_name":"Manchester, 40962, Kentucky, United States","relevance":1,"center":[-83.767232,37.141201],"geometry":{"type":"Point","coordinates":[-83.767232,37.141201]},"bbox":[-83.96957998089061,36.943115077831166,-83.52802226145461,37.33882210766987],"properties":{"title":"Manchester"},"context":[{"id":"postcode-us.238657257","text":"40962"},{"id":"province.971454021","text":"Kentucky"},{"id":"country.4150104525","text":"United States"}]},{"id":"city.37355","type":"Feature","text":"Manchester","place_name":"Manchester, 37355, Tennessee, United States","relevance":1,"center":[-86.073429,35.502458],"geometry":{"type":"Point","coordinates":[-86.073429,35.502458]},"bbox":[-86.24529792238344,35.343730817708256,-85.89946409474979,35.6609362086282],"properties":{"title":"Manchester"},"context":[{"id":"postcode-us.1967114929","text":"37355"},{"id":"province.319054371","text":"Tennessee"},{"id":"country.4150104525","text":"United States"}]},{"id":"city.52057","type":"Feature","text":"Manchester","place_name":"Manchester, 52057, Iowa, United States","relevance":1,"center":[-91.450368,42.490013],"geometry":{"type":"Point","coordinates":[-91.450368,42.490013]},"bbox":[-91.57910598033276,42.361747362329275,-91.31490101740947,42.61688961052635],"properties":{"title":"Manchester"},"context":[{"id":"postcode-us.1664645206","text":"52057"},{"id":"province.3529999094","text":"Iowa"},{"id":"country.4150104525","text":"United States"}]},{"id":"city.48158","type":"Feature","text":"Manchester","place_name":"Manchester, 48158, Michigan, United States","relevance":1,"center":[-84.042118,42.161379],"geometry":{"type":"Point","coordinates":[-84.042118,42.161379]},"bbox":[-84.17217198294256,42.07212133192145,-83.8935120175224,42.25007863309153],"properties":{"title":"Manchester"},"context":[{"id":"postcode-us.4061196615","text":"48158"},{"id":"province.696512852","text":"Michigan"},{"id":"country.4150104525","text":"United States"}]}],"attribution":"<a href='https://www.mapbox.com/about/maps/' target='_blank'>&copy; Mapbox</a>"}