{"type":"FeatureCollection","query":["memphis"],"features":[{"id":"city.38103","type":"Feature","text":"Memphis","place_name":"Memphis, 38122, Tennessee, United States","relevance":1,"center":[-89.941697,35.147502],"geometry":{"type":"Point","coordinates":[-89.941697,35.147502]},"bbox":[-90.31030696994897,34.99418064105769,-89.73315901687852,35.300457934321805],"properties":{"title":"Memphis"},"context":[{"id":"postcode-us.3144557179","text":"38122"},{"id":"province.319054371","text":"Tennessee"},{"id":"country.4150104525","text":"United States"}]},{"id":"city.79245","type":"Feature","text":"Memphis","place_name":"Memphis, 79245, Texas, United States","relevance":1,"center":[-100.505062,34.872789],"geometry":{"type":"Point","coordinates":[-100.505062,34.872789]},"bbox":[-100.66918896710897,34.56064383077608,-100.39481001760574,35.1831513379684],"properties":{"title":"Memphis"},"context":[{"id":"postcode-us.427919780","text":"79245"},{"id":"province.1000418602","text":"Texas"},{"id":"country.4150104525","text":"United States"}]},{"id":"city.63555","type":"Feature","text":"Memphis","place_name":"Memphis, 63555, Missouri, United States","relevance":1,"center":[-92.175848,40.475218],"geometry":{"type":"Point","coordinates":[-92.175848,40.475218]},"bbox":[-92.35054998288325,40.34790715784483,-92.02186901751337,40.60227979524955],"properties":{"title":"Memphis"},"context":[{"id":"postcode-us.58191932","text":"63555"},{"id":"province.3294535744","text":"Missouri"},{"id":"country.4150104525","text":"United States"}]},{"id":"city.48041","type":"Feature","text":"Memphis","place_name":"Memphis, 48041, Michigan, United States","relevance":1,"center":[-82.803867,42.933663],"geometry":{"type":"Point","coordinates":[-82.803867,42.933663]},"bbox":[-82.86694898213429,42.87780572057241,-82.73900103017685,42.986692569327076],"properties":{"title":"Memphis"},"context":[{"id":"postcode-us.1447018708","text":"48041"},{"id":"province.696512852","text":"Michigan"},{"id":"country.4150104525","text":"United States"}]},{"id":"city.47143","type":"Feature","text":"Memphis","place_name":"Memphis, 47143, Indiana, United States","relevance":1,"center":[-85.75521,38.471289],"geometry":{"type":"Point","coordinates":[-85.75521,38.471289]},"bbox":[-85.83317697961532,38.40420196197031,-85.70174305273657,38.538193678572085],"properties":{"title":"Memphis"},"context":[{"id":"postcode-us.1086071246","text":"47143"},{"id":"province.3248846408","text":"Indiana"},{"id":"country.4150104525","text":"United States"}]}],"attribution":"<a href='https://www.mapbox.com/about/maps/' target='_blank'>&copy; Mapbox</a>"}