{"type":"FeatureCollection","query":["milan"],"features":[{"id":"city.10718345","type":"Feature","text":"Milan","place_name":"Milan, 20121, MILANO, Italy","relevance":1,"center":[9.187508,45.472299],"geometry":{"type":"Point","coordinates":[9.187508,45.472299]},"bbox":[9.052358000000007,45.37493900000001,9.311936000000001,45.56592899999999],"properties":{"title":"Milan"},"context":[{"id":"postcode-it.2995","text":"20121"},{"id":"province.851189109","text":"MILANO"},{"id":"country.2118842266","text":"Italy"}]},{"id":"city.22675801","type":"Feature","text":"Milan","place_name":"Milan, 20121, MILANO, Italy","relevance":1,"center":[9.190874,45.468357],"geometry":{"type":"Point","coordinates":[9.190874,45.468357]},"bbox":[9.08878299999999,45.40712700000001,9.286772999999997,45.527939],"properties":{"title":"Milan"},"context":[{"id":"postcode-it.2995","text":"20121"},{"id":"province.851189109","text":"MILANO"},{"id":"country.2118842266","text":"Italy"}]},{"id":"city.63556","type":"Feature","text":"Milan","place_name":"Milan, 63556, Missouri, United States","relevance":1,"center":[-93.155366,40.194842],"geometry":{"type":"Point","coordinates":[-93.155366,40.194842]},"bbox":[-93.33971398215633,40.05112612610969,-92.8838020206328,40.33852082527675],"properties":{"title":"Milan"},"context":[{"id":"postcode-us.1414898951","text":"63556"},{"id":"province.3294535744","text":"Missouri"},{"id":"country.4150104525","text":"United States"}]},{"id":"city.3588","type":"Feature","text":"Milan","place_name":"Milan, 03588, New Hampshire, United States","relevance":1,"center":[-71.174573,44.619347],"geometry":{"type":"Point","coordinates":[-71.174573,44.619347]},"bbox":[-71.35612240854452,44.52470659620761,-71.02848101946977,44.71170738238691],"properties":{"title":"Milan"},"context":[{"id":"postcode-us.3172136588","text":"03588"},{"id":"province.3829989082","text":"New Hampshire"},{"id":"country.4150104525","text":"United States"}]},{"id":"city.31060","type":"Feature","text":"Milan","place_name":"Milan, 31060, Georgia, United States","relevance":1,"center":[-83.061167,31.974552],"geometry":{"type":"Point","coordinates":[-83.061167,31.974552]},"bbox":[-83.1852867616774,31.85172237081197,-82.96244351394967,32.09610247301019],"properties":{"title":"Milan"},"context":[{"id":"postcode-us.1179818748","text":"31060"},{"id":"province.2525851114","text":"Georgia"},{"id":"country.4150104525","text":"United States"}]}],"attribution":"<a href='https://www.mapbox.com/about/maps/' target='_blank'>&copy; Mapbox</a>"}