{"type":"FeatureCollection","query":["mumbai"],"features":[{"id":"city.12295411","type":"Feature","text":"Mumbai","place_name":"Mumbai, Maharashtra, India","relevance":1,"center":[72.886062,19.074935],"geometry":{"type":"Point","coordinates":[72.886062,19.074935]},"bbox":[72.77069100000001,18.879001999999993,72.98165900000001,19.278272999999988],"properties":{"title":"Mumbai"},"context":[{"id":"province.4224009162","text":"Maharashtra"},{"id":"country.2189592406","text":"India"}]},{"id":"city.12273886","type":"Feature","text":"Mumbai","place_name":"Mumbai, Maharashtra","relevance":1,"center":[72.825096,19.031709],"geometry":{"type":"Point","coordinates":[72.825096,19.031709]},"bbox":[72.80502299999999,19.000451999999996,72.84450500000003,19.071038999999985],"properties":{"title":"Mumbai"},"context":[{"id":"province.4224009162","text":"Maharashtra"}]}],"attribution":"<a href='https://www.mapbox.com/about/maps/' target='_blank'>&copy; Mapbox</a>"}