{"type":"FeatureCollection","query":["riyadh"],"features":[{"id":"city.11939753","type":"Feature","text":"Riyadh","place_name":"Riyadh, Ar Riyad, Saudi Arabia","relevance":1,"center":[46.714432,24.722269],"geometry":{"type":"Point","coordinates":[46.714432,24.722269]},"bbox":[46.504097,24.523489000000005,46.914368,24.934467000000005],"properties":{"title":"Riyadh"},"context":[{"id":"province.378444332","text":"Ar Riyad"},{"id":"country.3267341775","text":"Saudi Arabia"}]}],"attribution":"<a href='https://www.mapbox.com/about/maps/' target='_blank'>&copy; Mapbox</a>"}