{"type":"FeatureCollection","query":["shenzhen"],"features":[{"id":"city.22687656","type":"Feature","text":"Shenzhen","place_name":"Shenzhen, Guangdong, China","relevance":1,"center":[113.999251,22.540217],"geometry":{"type":"Point","coordinates":[113.999251,22.540217]},"bbox":[113.89209000000001,22.463387999999988,114.13970900000002,22.61586799999999],"properties":{"title":"Shenzhen"},"context":[{"id":"province.186418459","text":"Guangdong"},{"id":"country.1360165074","text":"China"}]},{"id":"city.12161853","type":"Feature","text":"Shenzhen","place_name":"Shenzhen, Guangdong, China","relevance":1,"center":[114.09778,22.548285],"geometry":{"type":"Point","coordinates":[114.09778,22.548285]},"bbox":[114.05422200000004,22.51572799999999,114.14794900000003,22.584214999999993],"properties":{"title":"Shenzhen"},"context":[{"id":"province.186418459","text":"Guangdong"},{"id":"country.1360165074","text":"China"}]},{"id":"city.22687657","type":"Feature","text":"Shenzhen","place_name":"Shenzhen, Guangdong, China","relevance":1,"center":[114.133015,22.693548],"geometry":{"type":"Point","coordinates":[114.133015,22.693548]},"bbox":[113.80715900000001,22.56303199999999,114.36528800000005,22.76098599999999],"properties":{"title":"Shenzhen"},"context":[{"id":"province.186418459","text":"Guangdong"},{"id":"country.1360165074","text":"China"}]}],"attribution":"<a href='https://www.mapbox.com/about/maps/' target='_blank'>&copy; Mapbox</a>"}