{"type":"FeatureCollection","query":["toledo"],"features":[{"id":"province.1717061240","type":"Feature","text":"Toledo","place_name":"Toledo, Spain","relevance":1,"center":[-4.102678,39.790404],"geometry":{"type":"Point","coordinates":[-4.102678,39.790404]},"bbox":[-5.406183690000007,39.25841677999998,-2.9082332900000067,40.31834080999998],"properties":{"title":"Toledo"},"context":[{"id":"country.1043386000","text":"Spain"}]},{"id":"province.821440288","type":"Feature","text":"Toledo","place_name":"Toledo, Belize","relevance":1,"center":[-88.924751,16.286078],"geometry":{"type":"Point","coordinates":[-88.924751,16.286078]},"bbox":[-89.2365122076722,15.879651999440288,-88.3863826161648,16.69184967722088],"properties":{"title":"Toledo"},"context":[{"id":"country.2773887635","text":"Belize"}]},{"id":"city.43604","type":"Feature","text":"Toledo","place_name":"Toledo, 43607, Ohio, United States","relevance":1,"center":[-83.620257,41.656661],"geometry":{"type":"Point","coordinates":[-83.620257,41.656661]},"bbox":[-83.7619569819484,41.58025939022245,-83.4323692160377,41.73285069664621],"properties":{"title":"Toledo"},"context":[{"id":"postcode-us.723884525","text":"43607"},{"id":"province.2820712142","text":"Ohio"},{"id":"country.4150104525","text":"United States"}]},{"id":"city.10775524","type":"Feature","text":"Toledo","place_name":"Toledo, Toledo, Spain","relevance":1,"center":[-4.03298,39.871626],"geometry":{"type":"Point","coordinates":[-4.03298,39.871626]},"bbox":[-4.066261,39.841232,-3.975098000000013,39.901306000000005],"properties":{"title":"Toledo"},"context":[{"id":"province.1717061240","text":"Toledo"},{"id":"country.1043386000","text":"Spain"}]},{"id":"city.22691090","type":"Feature","text":"Toledo","place_name":"Toledo, Toledo, Spain","relevance":1,"center":[-4.028295,39.869999],"geometry":{"type":"Point","coordinates":[-4.028295,39.869999]},"bbox":[-4.056701000000011,39.83717699999999,-3.93505800000001,39.90176799999998],"properties":{"title":"Toledo"},"context":[{"id":"province.1717061240","text":"Toledo"},{"id":"country.1043386000","text":"Spain"}]}],"attribution":"<a href='https://www.mapbox.com/about/maps/' target='_blank'>&copy; Mapbox</a>"}