{"type":"FeatureCollection","query":["waco"],"features":[{"id":"city.76701","type":"Feature","text":"Waco","place_name":"Waco, 76705, Texas, United States","relevance":1,"center":[-97.091892,31.576733],"geometry":{"type":"Point","coordinates":[-97.091892,31.576733]},"bbox":[-97.28972258237326,31.381596346812245,-96.91680140033473,31.771615545513125],"properties":{"title":"Waco"},"context":[{"id":"postcode-us.986575429","text":"76705"},{"id":"province.1000418602","text":"Texas"},{"id":"country.4150104525","text":"United States"}]},{"id":"city.68460","type":"Feature","text":"Waco","place_name":"Waco, 68460, Nebraska, United States","relevance":1,"center":[-97.425399,40.889322],"geometry":{"type":"Point","coordinates":[-97.425399,40.889322]},"bbox":[-97.52224798176945,40.76033119577117,-97.36806301871546,41.01739077711238],"properties":{"title":"Waco"},"context":[{"id":"postcode-us.421105527","text":"68460"},{"id":"province.1811079910","text":"Nebraska"},{"id":"country.4150104525","text":"United States"}]},{"id":"city.40385","type":"Feature","text":"Waco","place_name":"Waco, 40385, Kentucky, United States","relevance":1,"center":[-84.135999,37.781977],"geometry":{"type":"Point","coordinates":[-84.135999,37.781977]},"bbox":[-84.20755697611453,37.59612089404314,-84.07375501785042,37.86771264375683],"properties":{"title":"Waco"},"context":[{"id":"postcode-us.4022209798","text":"40385"},{"id":"province.971454021","text":"Kentucky"},{"id":"country.4150104525","text":"United States"}]},{"id":"city.30182","type":"Feature","text":"Waco","place_name":"Waco, 30182, Georgia, United States","relevance":1,"center":[-85.268162,33.647103],"geometry":{"type":"Point","coordinates":[-85.268162,33.647103]},"bbox":[-85.34273488782296,33.589076819626136,-85.1593042280294,33.70503724727837],"properties":{"title":"Waco"},"context":[{"id":"postcode-us.157209443","text":"30182"},{"id":"province.2525851114","text":"Georgia"},{"id":"country.4150104525","text":"United States"}]},{"id":"city.28169","type":"Feature","text":"Waco","place_name":"Waco, 28169, North Carolina, United States","relevance":1,"center":[-81.429549,35.358309],"geometry":{"type":"Point","coordinates":[-81.429549,35.358309]},"bbox":[-81.43864199915738,35.35138867375513,-81.41971903834316,35.36532348403917],"properties":{"title":"Waco"},"context":[{"id":"postcode-us.229307468","text":"28169"},{"id":"province.2516948401","text":"North Carolina"},{"id":"country.4150104525","text":"United States"}]}],"attribution":"<a href='https://www.mapbox.com/about/maps/' target='_blank'>&copy; Mapbox</a>"}