{"type":"FeatureCollection","query":["wellington"],"features":[{"id":"city.12351310","type":"Feature","text":"Wellington","place_name":"Wellington, Wellington Region, New Zealand","relevance":1,"center":[174.786633,-41.303207],"geometry":{"type":"Point","coordinates":[174.786633,-41.303207]},"bbox":[174.651917,-41.40411000000001,174.88252300000002,-41.19480100000001],"properties":{"title":"Wellington"},"context":[{"id":"province.2132819545","text":"Wellington Region"},{"id":"country.82898951","text":"New Zealand"}]},{"id":"city.79095","type":"Feature","text":"Wellington","place_name":"Wellington, 79095, Texas, United States","relevance":1,"center":[-100.181887,34.916679],"geometry":{"type":"Point","coordinates":[-100.181887,34.916679]},"bbox":[-100.43400898313021,34.74701961875396,-100.00037101684718,35.08433933397201],"properties":{"title":"Wellington"},"context":[{"id":"postcode-us.1408524264","text":"79095"},{"id":"province.1000418602","text":"Texas"},{"id":"country.4150104525","text":"United States"}]},{"id":"city.89444","type":"Feature","text":"Wellington","place_name":"Wellington, 89444, Nevada, United States","relevance":1,"center":[-119.4085,38.697505],"geometry":{"type":"Point","coordinates":[-119.4085,38.697505]},"bbox":[-119.58956598124041,38.41689435279303,-119.10649702318916,38.976934978242596],"properties":{"title":"Wellington"},"context":[{"id":"postcode-us.3704717276","text":"89444"},{"id":"province.2975076950","text":"Nevada"},{"id":"country.4150104525","text":"United States"}]},{"id":"city.67152","type":"Feature","text":"Wellington","place_name":"Wellington, 67152, Kansas, United States","relevance":1,"center":[-97.394245,37.274119],"geometry":{"type":"Point","coordinates":[-97.394245,37.274119]},"bbox":[-97.58360198304207,37.11359483690899,-97.24052001687686,37.43373609703779],"properties":{"title":"Wellington"},"context":[{"id":"postcode-us.1893128422","text":"67152"},{"id":"province.1877798576","text":"Kansas"},{"id":"country.4150104525","text":"United States"}]},{"id":"city.80549","type":"Feature","text":"Wellington","place_name":"Wellington, 80549, Colorado, United States","relevance":1,"center":[-105.059937,40.83336],"geometry":{"type":"Point","coordinates":[-105.059937,40.83336]},"bbox":[-105.17772398140008,40.66791818663156,-104.90572101982741,40.99834272991267],"properties":{"title":"Wellington"},"context":[{"id":"postcode-us.3504588203","text":"80549"},{"id":"province.3410545423","text":"Colorado"},{"id":"country.4150104525","text":"United States"}]}],"attribution":"<a href='https://www.mapbox.com/about/maps/' target='_blank'>&copy; Mapbox</a>"}